mcp_server_bailian_image/__init__.py
mcp_server_bailian_image/server.py
mcp_server_bailian_image-1.0.3.dist-info/METADATA
mcp_server_bailian_image-1.0.3.dist-info/WHEEL
mcp_server_bailian_image-1.0.3.dist-info/entry_points.txt
mcp_server_bailian_image-1.0.3.dist-info/top_level.txt
mcp_server_bailian_image-1.0.3.dist-info/RECORD
