Metadata-Version: 2.4
Name: mcp-server-bailian-image
Version: 1.0.3
Summary: 阿里云百炼-通义万相图像生成MCP服务器
Author-email: AliyunBailian <support@aliyun.com>
License-Expression: MIT
Project-URL: Homepage, https://github.com/aliyun/mcp-server-bailian-image
Project-URL: Repository, https://github.com/aliyun/mcp-server-bailian-image
Project-URL: Documentation, https://help.aliyun.com/zh/model-studio/text-to-image-v2-api-reference
Project-URL: Bug Reports, https://github.com/aliyun/mcp-server-bailian-image/issues
Keywords: mcp,model-context-protocol,aliyun,bailian,tongyi,wanxiang,image,text-to-image,generation,ai,artificial-intelligence,computer-vision
Classifier: Development Status :: 4 - Beta
Classifier: Intended Audience :: Developers
Classifier: Programming Language :: Python :: 3
Classifier: Programming Language :: Python :: 3.8
Classifier: Programming Language :: Python :: 3.9
Classifier: Programming Language :: Python :: 3.10
Classifier: Programming Language :: Python :: 3.11
Classifier: Programming Language :: Python :: 3.12
Classifier: Topic :: Software Development :: Libraries :: Python Modules
Classifier: Topic :: Scientific/Engineering :: Artificial Intelligence
Classifier: Topic :: Multimedia :: Graphics :: Graphics Conversion
Requires-Python: >=3.8
Requires-Dist: mcp>=1.0.0
Requires-Dist: dashscope>=1.0.0
Provides-Extra: dev
Requires-Dist: pytest>=7.0.0; extra == "dev"
Requires-Dist: pytest-asyncio>=0.21.0; extra == "dev"
Requires-Dist: black>=22.0.0; extra == "dev"
Requires-Dist: isort>=5.0.0; extra == "dev"
Requires-Dist: mypy>=1.0.0; extra == "dev"
